pactest/pactest.py
pactest-1.0.0.dist-info/METADATA
pactest-1.0.0.dist-info/WHEEL
pactest-1.0.0.dist-info/top_level.txt
pactest-1.0.0.dist-info/RECORD
