Metadata-Version: 2.1
Name: pactest
Version: 1.0.0
Summary: A simple package that prints test the upload packges to PyPi.
Home-page: UNKNOWN
Author: UNKNOWN
Author-email: UNKNOWN
License: UNKNOWN
Platform: UNKNOWN
